soumojit/__init__.py
soumojit/command.py
soumojit/text.json
soumojit-0.0.10.dist-info/METADATA
soumojit-0.0.10.dist-info/WHEEL
soumojit-0.0.10.dist-info/entry_points.txt
soumojit-0.0.10.dist-info/top_level.txt
soumojit-0.0.10.dist-info/RECORD
