Metadata-Version: 2.1
Name: soumojit
Version: 0.0.10
Summary: A pip - Card!
Home-page: https://github.com/Soumojit28/pip-card
Author: Soumojit Ash
Author-email: soumojitash@gmail.com
License: UNKNOWN
Platform: UNKNOWN
Classifier: Programming Language :: Python :: 3
Classifier: License :: OSI Approved :: MIT License
Classifier: Operating System :: OS Independent
Requires-Dist: rich
